pogo_api/__init__.py
pogo_api/endpoint.py
pogo_api/http.py
pogo_api/pascal_converter.py
pogo_api/route.py
pogo_api/version.py
pogo_api/websocket_endpoint.py
pogo_api/websocket_route.py
pogo_api-0.0.4.dist-info/LICENSE
pogo_api-0.0.4.dist-info/METADATA
pogo_api-0.0.4.dist-info/WHEEL
pogo_api-0.0.4.dist-info/top_level.txt
pogo_api-0.0.4.dist-info/RECORD
