Metadata-Version: 2.1
Name: pogo-api
Version: 0.0.4
Summary: Pogo Api
Home-page: https://github.com/nymann/pogo-api
Maintainer: Kristian Nymann Jakobsen
Maintainer-email: kristian@nymann.dev
Requires-Python: >=3.10
License-File: LICENSE
Requires-Dist: fastapi
Provides-Extra: all
Requires-Dist: add-trailing-comma ; extra == 'all'
Requires-Dist: black ; extra == 'all'
Requires-Dist: isort ; extra == 'all'
Requires-Dist: mypy ; extra == 'all'
Requires-Dist: nitpick ; extra == 'all'
Requires-Dist: wemake-python-styleguide ; extra == 'all'
Requires-Dist: python-dotenv ; extra == 'all'
Requires-Dist: pytest ; extra == 'all'
Requires-Dist: pytest-cov ; extra == 'all'
Requires-Dist: pytest-mock ; extra == 'all'
Provides-Extra: dev
Requires-Dist: add-trailing-comma ; extra == 'dev'
Requires-Dist: black ; extra == 'dev'
Requires-Dist: isort ; extra == 'dev'
Requires-Dist: mypy ; extra == 'dev'
Requires-Dist: nitpick ; extra == 'dev'
Requires-Dist: wemake-python-styleguide ; extra == 'dev'
Requires-Dist: python-dotenv ; extra == 'dev'
Provides-Extra: package
Requires-Dist: twine ; extra == 'package'
Requires-Dist: wheel ; extra == 'package'
Provides-Extra: tests
Requires-Dist: pytest ; extra == 'tests'
Requires-Dist: pytest-cov ; extra == 'tests'
Requires-Dist: pytest-mock ; extra == 'tests'
